Metadata-Version: 2.1
Name: MyTxtPdf
Version: 1.0.2
Summary: Teste referente a pubiclação do pacote
Home-page: https://github.com/pedrotercio14/Pacote-InfoPdf.git
Author: Pedro Tércio 
Author-email: pedrotercio@gmail.com
License: MIT License
Keywords: pdf
License-File: LICENSE
